{
    "33F80913-7FED-40B4-8C5B-45BBD26155A7": {
        "dep_id": "33F80913-7FED-40B4-8C5B-45BBD26155A7",
        "dep_cname": "生醫產業經營與法律學分學程",
        "dep_ename": "Program of Law and Management of Biomedical Industry",
        "1": {
            "1121_557900": {
                "acy": "112",
                "sem": "1",
                "cos_id": "557900",
                "cos_code": "LWLW30123",
                "num_limit": "9999",
                "dep_limit": "N",
                "URL": "",
                "cos_cname": "民法債編總論",
                "cos_credit": "3.00",
                "cos_hours": "3.00",
                "TURL": "",
                "teacher": "邱羽凡",
                "cos_time": "T567-AB102[GF]",
                "memo": "須修過民法總則。\n實地線上混合教學課程。\n陽明校區：線上，請向教師索取線上連結。",
                "cos_ename": "Civil Law: General Provisions of Obligations",
                "brief": "",
                "degree": "1",
                "dep_id": "PCF",
                "dep_primary": "1",
                "dep_cname": "生醫產業經營與法律學分學程",
                "dep_ename": "Program of Law and Management of Biomedical Industry",
                "cos_type": "選修",
                "cos_type_e": "Elective",
                "crsoutline_type": "data",
                "reg_num": "0",
                "depType": "P"
            },
            "1121_557915": {
                "acy": "112",
                "sem": "1",
                "cos_id": "557915",
                "cos_code": "LWLW30086",
                "num_limit": "9999",
                "dep_limit": "N",
                "URL": "",
                "cos_cname": "專利法與實務專題",
                "cos_credit": "3.00",
                "cos_hours": "3.00",
                "TURL": "",
                "teacher": "劉尚志、陳在方、陳豐奇、黃崧洺",
                "cos_time": "S234-MB1069[GF]",
                "memo": "",
                "cos_ename": "Special Topics on Patent Law and Practice",
                "brief": "",
                "degree": "1",
                "dep_id": "PCF",
                "dep_primary": "1",
                "dep_cname": "生醫產業經營與法律學分學程",
                "dep_ename": "Program of Law and Management of Biomedical Industry",
                "cos_type": "選修",
                "cos_type_e": "Elective",
                "crsoutline_type": "data",
                "reg_num": "0",
                "depType": "P"
            }
        },
        "costype": {
            "1121_557900": {
                "跨校區課程_跨校區課程": {
                    "course_category_cname": "跨校區課程_跨校區課程",
                    "course_category_ename": "Cross-Campus Course_Cross-Campus Course",
                    "course_category_type": "57",
                    "GECIName": "",
                    "GECIEngName": ""
                }
            },
            "1121_557915": {
                "智財權課程_智財權": {
                    "course_category_cname": "智財權課程_智財權",
                    "course_category_ename": "Intellectual Property_IP",
                    "course_category_type": "8",
                    "GECIName": "",
                    "GECIEngName": ""
                }
            }
        },
        "brief": {
            "1121_557900": {
                "": {
                    "brief_code": "",
                    "brief": ""
                }
            },
            "1121_557915": {
                "": {
                    "brief_code": "",
                    "brief": ""
                }
            }
        },
        "language": {
            "1121_557900": {
                "授課語言代碼": "zh-tw"
            },
            "1121_557915": {
                "授課語言代碼": "zh-tw"
            }
        }
    }
}